wallpaper/server.py
wallpaper_mcp_server-0.1.0.dist-info/licenses/LICENSE
wallpaper_mcp_server-0.1.0.dist-info/METADATA
wallpaper_mcp_server-0.1.0.dist-info/WHEEL
wallpaper_mcp_server-0.1.0.dist-info/entry_points.txt
wallpaper_mcp_server-0.1.0.dist-info/top_level.txt
wallpaper_mcp_server-0.1.0.dist-info/RECORD
